gvmkit_build-0.3.19.dist-info/METADATA
gvmkit_build-0.3.19.dist-info/WHEEL
gvmkit_build-0.3.19.dist-info/license_files/LICENSE
gvmkit_build/__init__.py
gvmkit_build/__main__.py
gvmkit_build-0.3.19.data/scripts/gvmkit-build
gvmkit_build-0.3.19.dist-info/RECORD
