Metadata-Version: 2.1
Name: gvmkit-build
Version: 0.3.19
Classifier: Development Status :: 4 - Beta
Classifier: Environment :: Console
Classifier: Intended Audience :: Developers
Classifier: License :: OSI Approved :: GNU General Public License v3 (GPLv3)
Classifier: Operating System :: OS Independent
Classifier: Programming Language :: Python
Classifier: Programming Language :: Python :: 3.8
Classifier: Programming Language :: Python :: 3.9
Classifier: Programming Language :: Python :: 3.10
Classifier: Programming Language :: Python :: 3.11
Classifier: Programming Language :: Python :: 3.12
Classifier: Programming Language :: Python :: 3.13
Classifier: Programming Language :: Python :: 3 :: Only
Classifier: Programming Language :: Rust
License-File: LICENSE
Summary: Golem VM Image builder.
Keywords: Golem
Author: Golem Factory <contact@golem.network>
Author-email: Golem Factory <contact@golem.network>
License: GPL-3.0
Requires-Python: >=3.8
Project-URL: repository, https://github.com/golemfactory/gvmkit-build-rs
